cqljupyter/__init__.py
cqljupyter/__main__.py
cqljupyter/args.py
cqljupyter/cqlsh.py
cqljupyter/images.py
cqljupyter/install.py
cqljupyter/kernel.py
cqljupyter-1.0.3.dist-info/LICENSE.txt
cqljupyter-1.0.3.dist-info/METADATA
cqljupyter-1.0.3.dist-info/WHEEL
cqljupyter-1.0.3.dist-info/top_level.txt
cqljupyter-1.0.3.dist-info/RECORD
