Metadata-Version: 2.1
Name: cqljupyter
Version: 1.0.3
Summary: CQL kernel for Jupyter based on Cassandra CQLSH
Home-page: https://github.com/bschoening/cqljupyter
Author: Brad Schoening, Steven Lowenthal & Apache Cassandra Developers
License: Apache
Keywords: cql,cassandra
Platform: UNKNOWN
Classifier: Development Status :: 5 - Production/Stable
Classifier: Intended Audience :: Developers
Classifier: Topic :: Software Development :: Build Tools
Classifier: License :: OSI Approved :: Apache Software License
Classifier: Programming Language :: Python :: 3
Classifier: Programming Language :: Python :: 3.6
Classifier: Programming Language :: Python :: 3.7
Classifier: Programming Language :: Python :: 3.8
Classifier: Programming Language :: Python :: 3.9
License-File: LICENSE.txt
Requires-Dist: cqlsh
Requires-Dist: ipython
Requires-Dist: jupyter-client
Requires-Dist: notebook
Requires-Dist: cassandra-driver (>=3.25)
